filehandls/__init__.py
filehandls/core.py
filehandls-0.1.1.dist-info/METADATA
filehandls-0.1.1.dist-info/WHEEL
filehandls-0.1.1.dist-info/top_level.txt
filehandls-0.1.1.dist-info/RECORD
